[
  {
    "source_idiom": "sorriso de uma orelha a outra",
    "target_idiom": "กระดี่ได้น้ำ",
    "source_meaning": "smile from ear to ear (large smile)",
    "target_meaning": "An overjoyed person."
  },
  {
    "source_idiom": "tremer as bases",
    "target_idiom": "กลัวเหมือนหนูกลัวแมว",
    "source_meaning": "to act apprehensively",
    "target_meaning": "to be cowardly."
  },
  {
    "source_idiom": "eu poderia comer um cavalo",
    "target_idiom": "กองทัพเดินด้วยท้อง",
    "source_meaning": "I could eat a horse (I am very hungry)",
    "target_meaning": "An army marches on its stomach."
  },
  {
    "source_idiom": "segurar vela",
    "target_idiom": "ก้างขวางคอ",
    "source_meaning": "to act as a third wheel (to be an unwanted third party accompanying two people on a date)",
    "target_meaning": "person who prevents a loving couple from enjoying a romantic moment."
  },
  {
    "source_idiom": "arregaçar as mangas",
    "target_idiom": "การลงมือ",
    "source_meaning": "to roll up one's sleeves",
    "target_meaning": "abstract noun of ลงมือ (long-mʉʉ)"
  },
  {
    "source_idiom": "jogar bola",
    "target_idiom": "การลงขัน",
    "source_meaning": "to play association football",
    "target_meaning": "abstract noun of ลงขัน (long-kǎn)"
  },
  {
    "source_idiom": "trocar seis por meia dúzia",
    "target_idiom": "กำขี้ดีกว่ากำตด",
    "source_meaning": "six of one, half a dozen of the other (to take a course of action that doesn’t make a difference)",
    "target_meaning": "something is better than nothing; half a loaf is better than none."
  },
  {
    "source_idiom": "ver o sol nascer quadrado",
    "target_idiom": "กินข้าวแดง",
    "source_meaning": "to serve time",
    "target_meaning": "to be imprisoned for a crime."
  },
  {
    "source_idiom": "em cima",
    "target_idiom": "เกาะชายกระโปรง",
    "source_meaning": "depending on or sustaining from (someone or something), chiefly in an unfair way, like taking advantage",
    "target_meaning": "to depend on a woman for livelihood."
  },
  {
    "source_idiom": "à frente de seu tempo",
    "target_idiom": "แก่แดด",
    "source_meaning": "ahead of one's time (in advance of commonly accepted ideas)",
    "target_meaning": "precocious."
  },
  {
    "source_idiom": "tosse de cachorro",
    "target_idiom": "ไก่โห่",
    "source_meaning": "barking cough (a loud, intense cough)",
    "target_meaning": "cockcrow."
  },
  {
    "source_idiom": "fazer média",
    "target_idiom": "เข้าเมืองตาหลิ่วต้องหลิ่วตาตาม",
    "source_meaning": "to adopt certain ideas or attitudes that would make someone accepted by someone else or a group",
    "target_meaning": "to follow local custom; to follow the majority."
  },
  {
    "source_idiom": "o pão que o diabo amassou",
    "target_idiom": "งอมพระราม",
    "source_meaning": "great suffering or strife in one's life",
    "target_meaning": "in dire straits; experiencing great hardship; undergoing severe suffering."
  },
  {
    "source_idiom": "bala na agulha",
    "target_idiom": "โจรห้าร้อย",
    "source_meaning": "ballsiness, toughness, courage",
    "target_meaning": "bold, reckless criminal or outlaw."
  },
  {
    "source_idiom": "deixar barato",
    "target_idiom": "เชือดไก่ให้ลิงดู",
    "source_meaning": "to not punish someone enough or at all for something wrong they did",
    "target_meaning": "to punish someone as an example for another."
  },
  {
    "source_idiom": "mais velho que o cagar em cócoras",
    "target_idiom": "เฒ่าหัวงู",
    "source_meaning": "to be old as the hills, to be older than dirt",
    "target_meaning": "dirty old man."
  },
  {
    "source_idiom": "fazer hora",
    "target_idiom": "ซื้อเวลา",
    "source_meaning": "to take too much time on purpose; to stall, waste time",
    "target_meaning": "to buy time."
  },
  {
    "source_idiom": "encontro às cegas",
    "target_idiom": "ดอกฟ้ากับหมาวัด",
    "source_meaning": "blind date (romantic meeting between two people who have never met before)",
    "target_meaning": "persons that do not seem suiting each other as romantic lovers because of their greatly different social standings."
  },
  {
    "source_idiom": "trazer ao mundo",
    "target_idiom": "ตกฟาก",
    "source_meaning": "to give birth",
    "target_meaning": "to be born; to be given birth; to be delivered."
  },
  {
    "source_idiom": "botar defeito",
    "target_idiom": "ติเรือทั้งโกลน",
    "source_meaning": "to criticise something that is fine; to be excessively perfectionist",
    "target_meaning": "to criticise something whilst it is still incomplete."
  },
  {
    "source_idiom": "zerar a vida",
    "target_idiom": "ตีปีก",
    "source_meaning": "to feel an extremely deep sense of accomplishment",
    "target_meaning": "to be overjoyed; to be elated."
  },
  {
    "source_idiom": "acabar com",
    "target_idiom": "ถีบหัวส่ง",
    "source_meaning": "to exhaust, use up",
    "target_meaning": "to expel, drive out, or sever relations with someone, especially when that one is of no more use."
  },
  {
    "source_idiom": "fazer gato-sapato",
    "target_idiom": "ถอนหงอก",
    "source_meaning": "to humiliate, to play or to treat someone with despise",
    "target_meaning": "to treat an adult or senior with contempt or disrespect; to show contempt or disrespect towards an adult or senior; to subject an adult or senior to contempt or disrespect."
  },
  {
    "source_idiom": "lágrimas de crocodilo",
    "target_idiom": "น้ำตาจระเข้",
    "source_meaning": "crocodile tears (display of tears that is forced or false)",
    "target_meaning": "crocodile tear."
  },
  {
    "source_idiom": "maus lençóis",
    "target_idiom": "น้ำท่า",
    "source_meaning": "deep water (difficult or embarrassing situation)",
    "target_meaning": "water; body of water."
  },
  {
    "source_idiom": "sujar a imagem",
    "target_idiom": "ป้ายสี",
    "source_meaning": "to besmirch the reputation of a person or thing",
    "target_meaning": "to slander; to smear; to sully, vilify, or soil a good name, reputation, etc."
  },
  {
    "source_idiom": "botar pra quebrar",
    "target_idiom": "ปิดทองหลังพระ",
    "source_meaning": "to do something well and willingly",
    "target_meaning": "to do good deeds without seeking attention or praise."
  },
  {
    "source_idiom": "fazer aniversário",
    "target_idiom": "ปีหน้าฟ้าใหม่",
    "source_meaning": "to turn years, to have a birthday",
    "target_meaning": "new year; next year; year to come; year ahead."
  },
  {
    "source_idiom": "por via das dúvidas",
    "target_idiom": "เป็นหูเป็นตา",
    "source_meaning": "just in case, just to be on the safe side",
    "target_meaning": "to be on guard or vigilant (on behalf of or for the sake of someone)"
  },
  {
    "source_idiom": "desde que eu me conheço por gente",
    "target_idiom": "แผลเก่า",
    "source_meaning": "since I remember",
    "target_meaning": "unforgettable painful memory."
  },
  {
    "source_idiom": "botar a mão no fogo",
    "target_idiom": "ฝากผีฝากไข้",
    "source_meaning": "to vouch for; to trust (someone) with one's life [ ]",
    "target_meaning": "to entrust one's life to someone; to ask someone to take care of one until one's last breath."
  },
  {
    "source_idiom": "enfiar o pé na jaca",
    "target_idiom": "มือเติบ",
    "source_meaning": "to do something excessively (e.g. to eat too much)",
    "target_meaning": "to lack restraint in spending money; to spend much more money than is necessary or wise; to be prodigal; to be extravagant."
  },
  {
    "source_idiom": "ser mais fácil uma cobra fumar do que",
    "target_idiom": "ลม ๆ แล้ง ๆ",
    "source_meaning": "indicates that something is extremely unlikely; when pigs fly; to find hen's teeth.",
    "target_meaning": "not likely to come true, not likely to happen; fantastic, irrational, groundless; futile, useless."
  },
  {
    "source_idiom": "misturar alhos com bugalhos",
    "target_idiom": "ลูกไม้หล่นไม่ไกลต้น",
    "source_meaning": "mix apples and oranges",
    "target_meaning": "the apple does not fall far from the tree"
  },
  {
    "source_idiom": "dar em cima de",
    "target_idiom": "เล่นหูเล่นตา",
    "source_meaning": "to hit on (to approach seeking romance, love, sex, etc)",
    "target_meaning": "to flirt with the eyes; to make eyes at."
  },
  {
    "source_idiom": "qualquer dia desses",
    "target_idiom": "วันดีคืนดี",
    "source_meaning": "one of these days (some time in the future)",
    "target_meaning": "one fine day."
  },
  {
    "source_idiom": "ficar para trás",
    "target_idiom": "เลื่อยขาเก้าอี้",
    "source_meaning": "to be superseded",
    "target_meaning": "to unseat; to dethrone; to topple"
  },
  {
    "source_idiom": "Inês é morta",
    "target_idiom": "วัวหายล้อมคอก",
    "source_meaning": "it's too late; what's done is done",
    "target_meaning": "to close the stable door after the horse has bolted."
  },
  {
    "source_idiom": "fazer de conta",
    "target_idiom": "สร้างภาพ",
    "source_meaning": "to pretend, to make believe",
    "target_meaning": "to create, publish, or promote a good image (of, about, etc); to propagandise (a good point of); to pretend, to act, or to put on an act (to make oneself, someone, or something look good); to be pretentious, fake, insincere, ingenuine, or hypocritic."
  },
  {
    "source_idiom": "força do hábito",
    "target_idiom": "สันดอนขุดง่าย สันดานขุดยาก",
    "source_meaning": "the tendency of doing something because it is a habit even when it is not necessary or expected",
    "target_meaning": "it is not easy to fix a bad habit."
  },
  {
    "source_idiom": "república das bananas",
    "target_idiom": "สาธารณรัฐกล้วย",
    "source_meaning": "banana republic (country dependent on a single export commodity with a corrupt dictatorial government)",
    "target_meaning": "banana republic"
  },
  {
    "source_idiom": "mina de ouro",
    "target_idiom": "สายป่าน",
    "source_meaning": "gold mine (very profitable economic venture)",
    "target_meaning": "resources, especially for use in producing more wealth or advancing a project."
  },
  {
    "source_idiom": "sem eira nem beira",
    "target_idiom": "สิ้นไร้ไม้ตอก",
    "source_meaning": "destitute; penniless (extremely poor)",
    "target_meaning": "very impoverished; experiencing serious financial hardship; penniless; penurious; extremely poor; needy."
  },
  {
    "source_idiom": "é mole ou quer mais",
    "target_idiom": "สิบปากว่าไม่เท่าตาเห็น",
    "source_meaning": "can you believe it?",
    "target_meaning": "Seeing is believing."
  },
  {
    "source_idiom": "cozinhar o galo",
    "target_idiom": "สีซอให้ควายฟัง",
    "source_meaning": "not to do anything productive; to fool around",
    "target_meaning": "to waste time reasoning with a fool; to waste time giving advice, instruction, or explanation to a fool."
  },
  {
    "source_idiom": "pedaço de mau caminho",
    "target_idiom": "เสือผู้หญิง",
    "source_meaning": "hunk, stud (an attractive man)",
    "target_meaning": "lady's man; womanizer."
  },
  {
    "source_idiom": "quinta coluna",
    "target_idiom": "หนอนบ่อนไส้",
    "source_meaning": "fifth column (a group of people which clandestinely undermines a larger group)",
    "target_meaning": "spy; inside agent; mole."
  },
  {
    "source_idiom": "santo do pau oco",
    "target_idiom": "หน้าซื่อใจคด",
    "source_meaning": "holier-than-thou (hypocritically or self-righteously pious)",
    "target_meaning": "hypocritical"
  },
  {
    "source_idiom": "lobo em pele de cordeiro",
    "target_idiom": "หน้าเนื้อใจเสือ",
    "source_meaning": "wolf in sheep's clothing (a disguised danger)",
    "target_meaning": "good or kind on the appearance, but actually wicked or evil."
  },
  {
    "source_idiom": "um ou outro",
    "target_idiom": "หนึ่งในตองอู",
    "source_meaning": "one or another (a very small subset)",
    "target_meaning": "exceptional person; the smartest person; the one of a kind; the one and only."
  },
  {
    "source_idiom": "conhecer como a palma da mão",
    "target_idiom": "หมองูตายเพราะงู",
    "source_meaning": "to know like the back of one's hand (to be intimately or highly knowledgeable about)",
    "target_meaning": "one who perishes because of something which one has the best knowledge about or is very familiar with."
  },
  {
    "source_idiom": "ser de comer rezando",
    "target_idiom": "หมาไม่แดก",
    "source_meaning": "to be exceptionally delicious",
    "target_meaning": "extremely undelicious; very unpleasant to the taste."
  },
  {
    "source_idiom": "pular a cerca",
    "target_idiom": "หักหลัง",
    "source_meaning": "to cheat (on one's partner)",
    "target_meaning": "to betray."
  },
  {
    "source_idiom": "nada a ver",
    "target_idiom": "หัวขี้เลื่อย",
    "source_meaning": "nonsensical; absurd",
    "target_meaning": "stupid; idiotic; unintelligent."
  },
  {
    "source_idiom": "antes de mais nada",
    "target_idiom": "หัวโต๊ะ",
    "source_meaning": "most importantly; primarily; mainly; chiefly; first and foremost",
    "target_meaning": "head; leader; chief; chairperson; president; presiding officer."
  },
  {
    "source_idiom": "sem tamanho",
    "target_idiom": "ใหญ่หลวง",
    "source_meaning": "massive, gigantic, humongous",
    "target_meaning": "great (in size or effect)."
  },
  {
    "source_idiom": "com tudo",
    "target_idiom": "อำนาจบาตรใหญ่",
    "source_meaning": "with total power or will",
    "target_meaning": "power or authority (when exercised oppressively or abusively)."
  },
  {
    "source_idiom": "se a carapuça serviu",
    "target_idiom": "เอาใจเขามาใส่ใจเรา",
    "source_meaning": "if the shoe fits; if the cap fits",
    "target_meaning": "to put oneself in someone's shoes."
  },
  {
    "source_idiom": "ser um livro aberto",
    "target_idiom": "เอาถ่าน",
    "source_meaning": "to be frank, loyal",
    "target_meaning": "to be serious, to be earnest, to be industrious."
  },
  {
    "source_idiom": "dormir sobre os louros",
    "target_idiom": "อุ่นใจ",
    "source_meaning": "to rest on one's laurels (to rely on a past success instead of trying to improve oneself further)",
    "target_meaning": "to rest easy; to rest assured; to be relieved."
  }
]
